textual_spinbox/__init__.py
textual_spinbox/demo.py
textual_spinbox/spinbox.py
textual_spinbox-0.8.2.dist-info/METADATA
textual_spinbox-0.8.2.dist-info/WHEEL
textual_spinbox-0.8.2.dist-info/entry_points.txt
textual_spinbox-0.8.2.dist-info/RECORD
