Metadata-Version: 2.4
Name: textual-spinbox
Version: 0.8.2
Summary: A simple spinbox widget for Textual
Author-email: Frisco Rose <friscorose@gmail.com>
Requires-Python: >=3.10
Requires-Dist: textual<2.1.3,>=1.0.0
